algviz/__init__.py
algviz/cursor.py
algviz/graph.py
algviz/graph_node_base.py
algviz/layouter.py
algviz/linked_list.py
algviz/logger.py
algviz/logo.py
algviz/map.py
algviz/sequencer.py
algviz/svg_graph.py
algviz/svg_table.py
algviz/table.py
algviz/tree.py
algviz/utility.py
algviz/vector.py
algviz/visual.py
algviz/lib/packing_solver_linux_amd64.so
algviz/lib/packing_solver_win_amd64.dll
algviz-0.3.1.dist-info/LICENSE
algviz-0.3.1.dist-info/METADATA
algviz-0.3.1.dist-info/WHEEL
algviz-0.3.1.dist-info/top_level.txt
algviz-0.3.1.dist-info/RECORD
