Metadata-Version: 2.1
Name: algviz
Version: 0.3.1
Summary: An algorithm visualization tool for jupyter notebook to show animation for vector, table, linked list, tree and graph data structures.
Home-page: https://algviz.com/
Author: zjl9959
Author-email: zjl9959@gmail.com
License: GPLv3
Project-URL: Documentation, https://algviz.readthedocs.io/en/latest/index.html
Project-URL: Issue Tracker, https://github.com/zjl9959/algviz/issues
Keywords: Algorithm Visualizer Animation Jupyter-notebook Graph
Classifier: Development Status :: 4 - Beta
Classifier: License :: OSI Approved :: GNU General Public License v3 (GPLv3)
Classifier: Topic :: Scientific/Engineering :: Visualization
Classifier: Programming Language :: Python :: 3
Requires-Python: >=3.8
License-File: LICENSE
Requires-Dist: graphviz !=0.18,<=0.20.1,>=0.8.4
Requires-Dist: ipykernel <=6.23.1,>=6.4.0
Requires-Dist: ipython <=8.12.0,>=8.0.0
